jwst_novt/__init__.py
jwst_novt/constants.py
jwst_novt/footprints.py
jwst_novt/run_notebook.py
jwst_novt/serve_novt.py
jwst_novt/timeline.py
jwst_novt/version.py
jwst_novt/data/JWSTlogo.png
jwst_novt/data/STScIlogo.png
jwst_novt/data/nircamlogo.png
jwst_novt/data/nirspeclogo.png
jwst_novt/data/voila.json
jwst_novt/interact/__init__.py
jwst_novt/interact/control_instruments.py
jwst_novt/interact/display.py
jwst_novt/interact/save_overlays.py
jwst_novt/interact/show_overlays.py
jwst_novt/interact/show_timeline.py
jwst_novt/interact/style_application.py
jwst_novt/interact/upload_data.py
jwst_novt/interact/utils.py
jwst_novt/interact/view_image.py
jwst_novt/interact/tests/__init__.py
jwst_novt/interact/tests/conftest.py
jwst_novt/interact/tests/test_control_instruments.py
jwst_novt/interact/tests/test_display.py
jwst_novt/interact/tests/test_save_overlays.py
jwst_novt/interact/tests/test_show_overlays.py
jwst_novt/interact/tests/test_show_timeline.py
jwst_novt/interact/tests/test_style_application.py
jwst_novt/interact/tests/test_upload_data.py
jwst_novt/notebooks/novt.ipynb
jwst_novt/notebooks/novt_interact.ipynb
jwst_novt/notebooks/novt_tools.ipynb
jwst_novt/notebooks/novt_voila.ipynb
jwst_novt/tests/__init__.py
jwst_novt/tests/test_footprints.py
jwst_novt/tests/test_run_notebook.py
jwst_novt/tests/test_serve_novt.py
jwst_novt/tests/test_timeline.py
jwst_novt-0.1.5.dist-info/licenses/LICENSE.rst
jwst_novt-0.1.5.dist-info/METADATA
jwst_novt-0.1.5.dist-info/WHEEL
jwst_novt-0.1.5.dist-info/entry_points.txt
jwst_novt-0.1.5.dist-info/top_level.txt
jwst_novt-0.1.5.dist-info/RECORD
