Metadata-Version: 2.4
Name: jwst_novt
Version: 0.1.5
Summary: JWST NIRSpec Observation Visualization Tool
Author: STScI
Project-URL: Homepage, https://github.com/spacetelescope/jwst_novt
Classifier: Intended Audience :: Science/Research
Classifier: Operating System :: OS Independent
Classifier: Programming Language :: Python :: 3
Classifier: Programming Language :: Python :: Implementation :: CPython
Classifier: Topic :: Scientific/Engineering :: Astronomy
Classifier: Topic :: Scientific/Engineering :: Physics
Requires-Python: <3.14,>=3.11
License-File: LICENSE.rst
Requires-Dist: astropy>=5.2.2
Requires-Dist: jwst_gtvt>=1.0.0
Requires-Dist: numpy>=1.24.3
Requires-Dist: pandas>=2.0.1
Requires-Dist: pysiaf>=0.19.1
Requires-Dist: regions>=0.7
Requires-Dist: requests>=2.28
Requires-Dist: setuptools>=61.2
Provides-Extra: interact
Requires-Dist: bqplot>=0.12.37; extra == "interact"
Requires-Dist: ipykernel>=6.19.4; extra == "interact"
Requires-Dist: ipyvuetify>=1.7.0; extra == "interact"
Requires-Dist: ipywidgets>=8.0.4; extra == "interact"
Requires-Dist: jdaviz<4.5.0,>=4.3.0; extra == "interact"
Requires-Dist: pyyaml>=5.4.1; extra == "interact"
Requires-Dist: traitlets>=5.0.5; extra == "interact"
Requires-Dist: voila>=0.4; extra == "interact"
Provides-Extra: test
Requires-Dist: ruff>0.3; extra == "test"
Requires-Dist: pytest; extra == "test"
Requires-Dist: pytest-coverage; extra == "test"
Requires-Dist: pytest-mock; extra == "test"
Provides-Extra: docs
Requires-Dist: graphviz; extra == "docs"
Requires-Dist: stsci_rtd_theme; extra == "docs"
Requires-Dist: sphinx-astropy; extra == "docs"
Requires-Dist: sphinx_rtd_theme; extra == "docs"
Requires-Dist: sphinx-automodapi; extra == "docs"
Requires-Dist: sphinx-issues; extra == "docs"
Requires-Dist: tomli; extra == "docs"
Dynamic: license-file
